fcart.py
fcart-0.0.1.dist-info/METADATA
fcart-0.0.1.dist-info/WHEEL
fcart-0.0.1.dist-info/top_level.txt
fcart-0.0.1.dist-info/RECORD
